README.md
setup.py
spaint/__init__.py
spaint/ansi256.py
spaint/ansi8.py
spaint/colorsec.py
spaint/common.py
spaint/linux.py
spaint/spaint.py
spaint/win8.py
spaint.egg-info/PKG-INFO
spaint.egg-info/SOURCES.txt
spaint.egg-info/dependency_links.txt
spaint.egg-info/top_level.txt